DESCRIPTION
MANIFEST.in
README
README.rst
setup.py
django_utilities.egg-info/PKG-INFO
django_utilities.egg-info/SOURCES.txt
django_utilities.egg-info/dependency_links.txt
django_utilities.egg-info/entry_points.txt
django_utilities.egg-info/not-zip-safe
django_utilities.egg-info/top_level.txt
utilities/__init__.py
utilities/admin.py
utilities/decorators.py
utilities/fields.py
utilities/middleware.py
utilities/models.py
utilities/settings.py
utilities/urls.py
utilities/widgets.py
utilities/locale/ru/LC_MESSAGES/django.mo
utilities/locale/ru/LC_MESSAGES/django.po
utilities/management/__init__.py
utilities/management/commands/__init__.py
utilities/management/commands/imagekit_recache.py
utilities/management/commands/update_premissions.py
utilities/redsolution_setup/__init__.py
utilities/redsolution_setup/make.py
utilities/redsolution_setup/templates/utilities/redsolutioncms/base_utilities.html
utilities/redsolution_setup/templates/utilities/redsolutioncms/development.pyt
utilities/redsolution_setup/templates/utilities/redsolutioncms/settings.pyt
utilities/static/utilities/js/csrf.js
utilities/templates/admin/password_reset_complete.html
utilities/templates/admin/reset_password.html
utilities/templatetags/__init__.py
utilities/templatetags/utilities_tags.py