Metadata-Version: 1.0
Name: django-utilities
Version: 0.1.5
Summary: Django's set of utilities. Includes admin ImageField with preview, override for username,
Home-page: UNKNOWN
Author: Alexander Ivanov
Author-email: alexander.ivanov@redsolution.ru
License: GPLv3
Keywords: django utilities
Platform: UNKNOWN
Classifier: Development Status :: 3 - Alpha
Classifier: Framework :: Buildout
Classifier: Intended Audience :: Developers
Classifier: License :: OSI Approved :: GNU General Public License (GPL)
Classifier: Natural Language :: Russian
Classifier: Operating System :: Microsoft :: Windows
Classifier: Operating System :: Unix
Classifier: Programming Language :: Python :: 2.5
Classifier: Topic :: Software Development :: Version Control
